{
  "users": [
    {
      "id": "111111111",
      "username": "cryptoking",
      "firstName": "Sarah",
      "lastName": "Connor",
      "photoUrl": "https://images.unsplash.com/photo-1534528741775-53994a69daeb?w=120&h=120&fit=crop&crop=faces",
      "languageCode": "en",
      "registeredAt": "2026-06-01T12:00:00Z",
      "balanceTM": 4200,
      "balanceUSDT": 1.719,
      "lifetimeEarningsUSDT": 4.719,
      "referralEarningsUSDT": 1.2,
      "todayBonusUSDT": 0.462,
      "depositStatus": "Approved",
      "withdrawStatus": "None",
      "referralCount": 8,
      "isFrozen": false,
      "isBanned": false,
      "mandatoryCompleted": true,
      "uid": 117301
    },
    {
      "id": "222222222",
      "username": "tg_rich",
      "firstName": "Michael",
      "lastName": "Scott",
      "photoUrl": "https://images.unsplash.com/photo-1507003211169-0a1dd7228f2d?w=120&h=120&fit=crop&crop=faces",
      "languageCode": "en",
      "registeredAt": "2026-07-10T15:30:00Z",
      "balanceTM": 1500,
      "balanceUSDT": 0.43,
      "lifetimeEarningsUSDT": 0.43,
      "referralEarningsUSDT": 0,
      "todayBonusUSDT": 0.165,
      "depositStatus": "Approved",
      "withdrawStatus": "None",
      "referralCount": 0,
      "isFrozen": false,
      "isBanned": false,
      "uid": 117302
    },
    {
      "id": "333333333",
      "username": "new_joiner",
      "firstName": "Dwight",
      "lastName": "Schrute",
      "photoUrl": "https://images.unsplash.com/photo-1500648767791-00dcc994a43e?w=120&h=120&fit=crop&crop=faces",
      "languageCode": "de",
      "registeredAt": "2026-07-05T09:15:00Z",
      "balanceTM": 1500,
      "balanceUSDT": 0.83,
      "lifetimeEarningsUSDT": 0.83,
      "referralEarningsUSDT": 0,
      "todayBonusUSDT": 0.165,
      "depositStatus": "Approved",
      "withdrawStatus": "Approved",
      "referralCount": 2,
      "isFrozen": false,
      "isBanned": false,
      "uid": 117303
    },
    {
      "id": "444444444",
      "username": "frozentg",
      "firstName": "Jim",
      "lastName": "Halpert",
      "photoUrl": "https://images.unsplash.com/photo-1519085360753-af0119f7cbe7?w=120&h=120&fit=crop&crop=faces",
      "languageCode": "en",
      "registeredAt": "2026-07-08T11:45:00Z",
      "balanceTM": 0,
      "balanceUSDT": 0,
      "lifetimeEarningsUSDT": 0,
      "referralEarningsUSDT": 0,
      "todayBonusUSDT": 0,
      "depositStatus": "None",
      "withdrawStatus": "None",
      "referralCount": 0,
      "isFrozen": true,
      "isBanned": false,
      "uid": 117304
    },
    {
      "id": "555555555",
      "username": "banned_user",
      "firstName": "Pam",
      "lastName": "Beesly",
      "photoUrl": "https://images.unsplash.com/photo-1438761681033-6461ffad8d80?w=100&h=100&fit=crop&crop=faces",
      "languageCode": "en",
      "registeredAt": "2026-07-02T16:20:00Z",
      "balanceTM": 2000,
      "balanceUSDT": 1,
      "lifetimeEarningsUSDT": 1,
      "referralEarningsUSDT": 0,
      "todayBonusUSDT": 0.1,
      "depositStatus": "Approved",
      "withdrawStatus": "None",
      "referralCount": 0,
      "isFrozen": false,
      "isBanned": true,
      "uid": 117305
    }
  ],
  "tasks": [
    {
      "id": "mandatory_channel_1",
      "title": "TM_Digital",
      "description": "Join the official TM_Digital Telegram channel.",
      "type": "TelegramChannel",
      "rewardTM": 200,
      "link": "https://t.me/TM_Digital",
      "isMandatory": true,
      "displayOrder": 1,
      "isEnabled": true,
      "requiresVerification": true,
      "channelId": "-1003260376953"
    },
    {
      "id": "mandatory_channel_2",
      "title": "TM_Back",
      "description": "Join the official TM_Back Telegram channel.",
      "type": "TelegramChannel",
      "rewardTM": 150,
      "link": "https://t.me/TM_Back",
      "isMandatory": true,
      "displayOrder": 2,
      "isEnabled": true,
      "requiresVerification": true,
      "channelId": "-1001179648853"
    },
    {
      "id": "mandatory_channel_3",
      "title": "TM_With",
      "description": "Join the official TM_With Telegram channel.",
      "type": "TelegramChannel",
      "rewardTM": 150,
      "link": "https://t.me/TM_With",
      "isMandatory": true,
      "displayOrder": 3,
      "isEnabled": true,
      "requiresVerification": true,
      "channelId": "-1001873895959"
    },
    {
      "id": "task_optional_1",
      "title": "Follow TM Digital on X",
      "description": "Follow @TM_Digital on X (Twitter) for instant updates.",
      "type": "ExternalLink",
      "rewardTM": 100,
      "link": "https://x.com",
      "isMandatory": false,
      "displayOrder": 4,
      "isEnabled": true,
      "requiresVerification": true
    }
  ],
  "channels": [],
  "deposits": [
    {
      "id": "dep_1",
      "userId": "111111111",
      "userUsername": "cryptoking",
      "userFirstName": "Sarah",
      "amountUSDT": 2.5,
      "txid": "0xbc534a6ef8d7e63b1189cd1235bc6741ee235ef982c7a6fdf99214abce389c",
      "screenshotUrl": "https://images.unsplash.com/photo-1621761191319-c6fb62004040?w=300&h=400&fit=crop",
      "status": "Approved",
      "createdAt": "2026-06-05T14:30:00Z",
      "processedAt": "2026-06-05T14:45:00Z"
    },
    {
      "id": "dep_2",
      "userId": "222222222",
      "userUsername": "tg_rich",
      "userFirstName": "Michael",
      "amountUSDT": 1,
      "txid": "0x77ae6522c8a2b34c9c1b2f91a5e12dc4a5b6c7a8d42398ab716fe2a8d4e9c7a4",
      "screenshotUrl": "https://images.unsplash.com/photo-1621761191319-c6fb62004040?w=300&h=400&fit=crop",
      "status": "Approved",
      "createdAt": "2026-07-10T16:00:00Z",
      "processedAt": "2026-07-11T18:50:09.352Z"
    },
    {
      "id": "dep_3",
      "userId": "333333333",
      "userUsername": "new_joiner",
      "userFirstName": "Dwight",
      "amountUSDT": 1,
      "txid": "0x89ee12ff3142abde41c2c3e1e235cb2418a1a3e2c39d8ea4f9c12bcf39de2a3a",
      "screenshotUrl": "https://images.unsplash.com/photo-1621761191319-c6fb62004040?w=300&h=400&fit=crop",
      "status": "Approved",
      "createdAt": "2026-07-06T11:00:00Z",
      "processedAt": "2026-07-06T11:15:00Z"
    }
  ],
  "withdrawals": [
    {
      "id": "wd_1",
      "userId": "111111111",
      "userUsername": "cryptoking",
      "userFirstName": "Sarah",
      "amountUSDT": 0.5,
      "walletAddress": "TMyWalletAddressUSDT11111",
      "ruleId": "rule_1",
      "ruleDescription": "Rule 1 (0.1 - 1.0 USDT): Requires minimum $1.00 lifetime approved deposits.",
      "status": "Approved",
      "createdAt": "2026-06-12T10:00:00Z",
      "processedAt": "2026-06-12T10:30:00Z"
    },
    {
      "id": "wd_2",
      "userId": "333333333",
      "userUsername": "new_joiner",
      "userFirstName": "Dwight",
      "amountUSDT": 0.2,
      "walletAddress": "TMyWalletAddressUSDT33333",
      "ruleId": "rule_1",
      "ruleDescription": "Rule 1 (0.1 - 1.0 USDT): Requires minimum $1.00 lifetime approved deposits.",
      "status": "Approved",
      "createdAt": "2026-07-11T05:00:00Z",
      "processedAt": "2026-07-11T18:50:11.909Z"
    },
    {
      "id": "wd_1783795071817",
      "userId": "111111111",
      "userUsername": "cryptoking",
      "userFirstName": "Sarah",
      "amountUSDT": 1,
      "walletAddress": "TR7NHqJeE4ntYHg8Bbu96TJvsB5bK6a9j4",
      "ruleId": "rule_1",
      "ruleDescription": "Security Check (Anti-Fake Multi-Account Prevention): Requires a one-time minimum $1.00 approved deposit on BEP20 (BSC Network). Once verified, you unlock unlimited withdrawals for lifetime.",
      "status": "Approved",
      "createdAt": "2026-07-11T18:37:51.817Z",
      "processedAt": "2026-07-11T18:50:12.547Z"
    },
    {
      "id": "wd_1783904719648",
      "userId": "111111111",
      "userUsername": "cryptoking",
      "userFirstName": "Sarah",
      "amountUSDT": 1,
      "walletAddress": "0xyihhgrb",
      "ruleId": "rule_1",
      "ruleDescription": "Security Check (Anti-Fake Multi-Account Prevention): Requires a one-time minimum $1.00 approved deposit on BEP20 (BSC Network). Once verified, you unlock unlimited withdrawals for lifetime.",
      "status": "Rejected",
      "createdAt": "2026-07-13T01:05:19.648Z",
      "processedAt": "2026-07-13T01:05:37.124Z"
    }
  ],
  "withdrawalRules": [],
  "transactions": [
    {
      "id": "tx_gift_1784035135906_h752p",
      "userId": "222222222",
      "type": "Reward",
      "amountTM": 0,
      "amountUSDT": 0.1,
      "description": "Gift Code Claimed: TM-GFT-T0SR-WXDG",
      "createdAt": "2026-07-14T13:18:55.906Z"
    },
    {
      "id": "tx_gift_1784035080746_4j0em",
      "userId": "111111111",
      "type": "Reward",
      "amountTM": 0,
      "amountUSDT": 0.1,
      "description": "Gift Code Claimed: TM-GFT-9BKX-NJXZ",
      "createdAt": "2026-07-14T13:18:00.746Z"
    },
    {
      "id": "tx_gift_1784034860209_dfvws",
      "userId": "111111111",
      "type": "Reward",
      "amountTM": 0,
      "amountUSDT": 0.1,
      "description": "Gift Code Claimed: TM-GFT-FLPR-0ELM",
      "createdAt": "2026-07-14T13:14:20.209Z"
    },
    {
      "id": "tx_task_1783930504631",
      "userId": "111111111",
      "type": "Reward",
      "amountTM": 150,
      "amountUSDT": 0.15,
      "description": "Task completed: TM_With",
      "createdAt": "2026-07-13T08:15:04.631Z"
    },
    {
      "id": "tx_task_1783930494905",
      "userId": "111111111",
      "type": "Reward",
      "amountTM": 150,
      "amountUSDT": 0.15,
      "description": "Task completed: TM_Back",
      "createdAt": "2026-07-13T08:14:54.905Z"
    },
    {
      "id": "tx_task_1783930168547",
      "userId": "111111111",
      "type": "Reward",
      "amountTM": 200,
      "amountUSDT": 0.2,
      "description": "Task completed: TM_Digital",
      "createdAt": "2026-07-13T08:09:28.547Z"
    },
    {
      "id": "tx_1",
      "userId": "111111111",
      "type": "Reward",
      "amountTM": 200,
      "amountUSDT": 0.2,
      "description": "Completed Mandatory Task: Join Official Telegram Channel",
      "createdAt": "2026-06-01T12:05:00Z"
    },
    {
      "id": "tx_2",
      "userId": "111111111",
      "type": "Reward",
      "amountTM": 200,
      "amountUSDT": 0.2,
      "description": "Completed Mandatory Task: Join Official Chat Group",
      "createdAt": "2026-06-01T12:10:00Z"
    },
    {
      "id": "tx_3",
      "userId": "111111111",
      "type": "Reward",
      "amountTM": 100,
      "amountUSDT": 0.1,
      "description": "Completed Mandatory Task: Start TM Verification Bot",
      "createdAt": "2026-06-01T12:12:00Z"
    },
    {
      "id": "tx_4",
      "userId": "111111111",
      "type": "Deposit",
      "amountTM": 2500,
      "amountUSDT": 2.5,
      "description": "Approved Deposit of 2.5 USDT (TXID: 0xbc534a6ef8...)",
      "createdAt": "2026-06-05T14:45:00Z"
    },
    {
      "id": "tx_5",
      "userId": "111111111",
      "type": "Withdraw",
      "amountTM": -500,
      "amountUSDT": -0.5,
      "description": "Approved Withdrawal of 0.5 USDT to TMyWalletAddressUSDT11111",
      "createdAt": "2026-06-12T10:30:00Z"
    },
    {
      "id": "tx_6",
      "userId": "333333333",
      "type": "Deposit",
      "amountTM": 1000,
      "amountUSDT": 1,
      "description": "Approved Deposit of 1.0 USDT (TXID: 0x89ee12ff31...)",
      "createdAt": "2026-07-06T11:15:00Z"
    },
    {
      "id": "bonus_claim_1783795046529",
      "userId": "111111111",
      "type": "DailyBonus",
      "amountTM": 0,
      "amountUSDT": 0.15,
      "description": "Claimed Daily Staking Bonus for holding 3500 TM",
      "createdAt": "2026-07-11T18:37:26.518Z"
    },
    {
      "id": "tx_withdraw_sub_1783795071817",
      "userId": "111111111",
      "type": "Withdraw",
      "amountTM": 0,
      "amountUSDT": -1,
      "description": "Submitted withdrawal request for 1 USDT to TR7NHqJeE4ntYHg8Bbu96TJvsB5bK6a9j4 (Pending Approval)",
      "createdAt": "2026-07-11T18:37:51.817Z"
    },
    {
      "id": "tx_task_1783795177716",
      "userId": "111111111",
      "type": "Reward",
      "amountTM": 150,
      "amountUSDT": 0.15,
      "description": "Task completed: Follow TM Digital on Twitter/X",
      "createdAt": "2026-07-11T18:39:37.716Z"
    },
    {
      "id": "tx_task_1783795181395",
      "userId": "111111111",
      "type": "Reward",
      "amountTM": 50,
      "amountUSDT": 0.05,
      "description": "Task completed: Claim Daily Telegram Check-in",
      "createdAt": "2026-07-11T18:39:41.395Z"
    },
    {
      "id": "tx_dep_appr_1783795809353",
      "userId": "222222222",
      "type": "Deposit",
      "amountTM": 1000,
      "amountUSDT": 1,
      "description": "Approved deposit of 1 USDT. Credited 1000 TM.",
      "createdAt": "2026-07-11T18:50:09.353Z"
    },
    {
      "id": "tx_wd_appr_1783795811909",
      "userId": "333333333",
      "type": "Withdraw",
      "amountTM": 0,
      "amountUSDT": -0.2,
      "description": "Approved withdrawal of 0.2 USDT to TMyWalletAddressUSDT33333.",
      "createdAt": "2026-07-11T18:50:11.909Z"
    },
    {
      "id": "tx_wd_appr_1783795812547",
      "userId": "111111111",
      "type": "Withdraw",
      "amountTM": 0,
      "amountUSDT": -1,
      "description": "Approved withdrawal of 1 USDT to TR7NHqJeE4ntYHg8Bbu96TJvsB5bK6a9j4.",
      "createdAt": "2026-07-11T18:50:12.547Z"
    },
    {
      "id": "interest_auto_111111111_1783881060000",
      "userId": "111111111",
      "type": "DailyBonus",
      "amountTM": 0,
      "amountUSDT": 0.407,
      "description": "Automatic 12:01 AM Staking Interest (3,700 TM holding)",
      "createdAt": "2026-07-12T18:31:00.000Z"
    },
    {
      "id": "interest_auto_222222222_1783881060000",
      "userId": "222222222",
      "type": "DailyBonus",
      "amountTM": 0,
      "amountUSDT": 0.165,
      "description": "Automatic 12:01 AM Staking Interest (1,500 TM holding)",
      "createdAt": "2026-07-12T18:31:00.000Z"
    },
    {
      "id": "interest_auto_333333333_1783881060000",
      "userId": "333333333",
      "type": "DailyBonus",
      "amountTM": 0,
      "amountUSDT": 0.165,
      "description": "Automatic 12:01 AM Staking Interest (1,500 TM holding)",
      "createdAt": "2026-07-12T18:31:00.000Z"
    },
    {
      "id": "tx_withdraw_sub_1783904719655",
      "userId": "111111111",
      "type": "Withdraw",
      "amountTM": 0,
      "amountUSDT": -1,
      "description": "Submitted withdrawal request for 1 USDT to 0xyihhgrb (Pending Approval)",
      "createdAt": "2026-07-13T01:05:19.656Z"
    },
    {
      "id": "tx_wd_rej_1783904737124",
      "userId": "111111111",
      "type": "Withdraw",
      "amountTM": 0,
      "amountUSDT": 1,
      "description": "Rejected withdrawal of 1 USDT. Balance refunded.",
      "createdAt": "2026-07-13T01:05:37.124Z"
    },
    {
      "id": "interest_auto_111111111_1783967460000",
      "userId": "111111111",
      "type": "DailyBonus",
      "amountTM": 0,
      "amountUSDT": 0.462,
      "description": "Automatic 12:01 AM Staking Interest (4,200 TM holding)",
      "createdAt": "2026-07-13T18:31:00.000Z"
    },
    {
      "id": "interest_auto_222222222_1783967460000",
      "userId": "222222222",
      "type": "DailyBonus",
      "amountTM": 0,
      "amountUSDT": 0.165,
      "description": "Automatic 12:01 AM Staking Interest (1,500 TM holding)",
      "createdAt": "2026-07-13T18:31:00.000Z"
    },
    {
      "id": "interest_auto_333333333_1783967460000",
      "userId": "333333333",
      "type": "DailyBonus",
      "amountTM": 0,
      "amountUSDT": 0.165,
      "description": "Automatic 12:01 AM Staking Interest (1,500 TM holding)",
      "createdAt": "2026-07-13T18:31:00.000Z"
    }
  ],
  "transfers": [],
  "tickets": [
    {
      "id": "tick_1",
      "userId": "111111111",
      "userFirstName": "Sarah",
      "userUsername": "cryptoking",
      "subject": "USDT Deposit delay TRC20",
      "status": "Replied",
      "createdAt": "2026-06-05T14:35:00Z",
      "messages": [
        {
          "sender": "user",
          "text": "Hi, I sent 2.5 USDT on TRC20 but it has been 5 minutes and hasn't shown up. Can you check my TXID?",
          "createdAt": "2026-06-05T14:35:00Z"
        },
        {
          "sender": "admin",
          "text": "Hello Sarah! We verified your TXID: 0xbc534a6ef8... and have approved your deposit. 2500 TM has been credited to your balance.",
          "createdAt": "2026-06-05T14:45:00Z"
        }
      ]
    },
    {
      "id": "tick_2",
      "userId": "333333333",
      "userFirstName": "Dwight",
      "userUsername": "new_joiner",
      "subject": "Withdrawal Question",
      "status": "Replied",
      "createdAt": "2026-07-11T05:30:00Z",
      "messages": [
        {
          "sender": "user",
          "text": "I submit a withdraw of 0.2 USDT. When will this get approved? Thank you.",
          "createdAt": "2026-07-11T05:30:00Z"
        },
        {
          "sender": "admin",
          "text": "Ok bro wait",
          "createdAt": "2026-07-12T04:33:53.802Z"
        }
      ]
    }
  ],
  "settings": {
    "conversionRate": 1000,
    "referralRewardUSDT": 0.03,
    "referralRewardTM": 50,
    "dailyBonusRateUSDT": 0.11,
    "dailyBonusIntervalHours": 24,
    "dailyBonusEnabled": true,
    "walletAddressUSDT": "TR7NHqJeE4ntYHg8Bbu96TJvsB5bK6a9j4",
    "qrCodeUrl": "https://api.qrserver.com/v1/create-qr-code/?size=250x250&data=TR7NHqJeE4ntYHg8Bbu96TJvsB5bK6a9j4",
    "autoApprovalEnabled": false,
    "maintenanceMode": false,
    "announcement": "📢 TM Digital v1.2 Live! Complete your mandatory tasks to unlock your premium staking dashboard.",
    "mandatoryTaskCount": 3,
    "depositMinUSDT": 1,
    "referralMilestones": [
      {
        "count": 5,
        "rewardTM": 80
      },
      {
        "count": 10,
        "rewardTM": 200
      },
      {
        "count": 25,
        "rewardTM": 500
      },
      {
        "count": 50,
        "rewardTM": 1200
      },
      {
        "count": 100,
        "rewardTM": 2500
      }
    ],
    "withdrawEnabled": true,
    "withdrawDisabledMessage": "🚫 Withdrawals are temporarily unavailable. Please try again later.",
    "referralSystemEnabled": true,
    "referralRewardAmountUSD": 3,
    "referralMinWithdrawRequirementUSD": 10
  },
  "completedTasks": {
    "111111111": [
      "task_1",
      "task_2",
      "task_3",
      "task_6",
      "task_4",
      "mandatory_channel_1",
      "mandatory_channel_2",
      "mandatory_channel_3"
    ],
    "222222222": [
      "task_1"
    ],
    "333333333": [
      "task_1",
      "task_2",
      "task_3"
    ]
  },
  "claimedBonuses": {},
  "taskSubmissions": [],
  "notifications": [
    {
      "id": "notif_gift_1784035135906_yqpr5",
      "userId": "222222222",
      "title": "Gift Code Claimed! 🎁",
      "message": "Successfully claimed code TM-GFT-T0SR-WXDG! received +$0.10 USDT.",
      "type": "task_completed",
      "createdAt": "2026-07-14T13:18:55.906Z",
      "read": false
    },
    {
      "id": "notif_gift_1784035080746_7gz7a",
      "userId": "111111111",
      "title": "Gift Code Claimed! 🎁",
      "message": "Successfully claimed code TM-GFT-9BKX-NJXZ! received +$0.10 USDT.",
      "type": "task_completed",
      "createdAt": "2026-07-14T13:18:00.746Z",
      "read": false
    },
    {
      "id": "notif_gift_1784034860209_p6bfw",
      "userId": "111111111",
      "title": "Gift Code Claimed! 🎁",
      "message": "Successfully claimed code TM-GFT-FLPR-0ELM! received +$0.10 USDT.",
      "type": "task_completed",
      "createdAt": "2026-07-14T13:14:20.209Z",
      "read": false
    },
    {
      "id": "notif_1783930504632_task_mandatory_channel_3",
      "userId": "111111111",
      "title": "Task Completed! ✅",
      "message": "You completed \"TM_With\" and earned +150 TM!",
      "type": "task_completed",
      "createdAt": "2026-07-13T08:15:04.632Z",
      "read": false
    },
    {
      "id": "notif_1783930494905_task_mandatory_channel_2",
      "userId": "111111111",
      "title": "Task Completed! ✅",
      "message": "You completed \"TM_Back\" and earned +150 TM!",
      "type": "task_completed",
      "createdAt": "2026-07-13T08:14:54.905Z",
      "read": false
    },
    {
      "id": "notif_1783930168547_task_mandatory_channel_1",
      "userId": "111111111",
      "title": "Task Completed! ✅",
      "message": "You completed \"TM_Digital\" and earned +200 TM!",
      "type": "task_completed",
      "createdAt": "2026-07-13T08:09:28.547Z",
      "read": false
    },
    {
      "id": "notif_1783904737124_wd_rej",
      "userId": "111111111",
      "title": "Withdrawal Rejected! ❌",
      "message": "Your withdrawal request of 1 USDT was rejected. 1 USDT has been refunded to your balance.",
      "type": "withdraw_approved",
      "createdAt": "2026-07-13T01:05:37.124Z",
      "read": false
    }
  ],
  "lastInterestPayout": "2026-07-14T13:03:04.682Z",
  "giftCodes": [
    {
      "code": "TM-GFT-SIC7-DUKO",
      "rewardAmount": 0.1,
      "maxClaims": 1,
      "claimsCount": 0,
      "isEnabled": true,
      "createdAt": "2026-07-14T13:07:15.846Z",
      "claimedBy": []
    },
    {
      "code": "TM-GFT-TYMW-2EKG",
      "rewardAmount": 0.1,
      "maxClaims": 1,
      "claimsCount": 0,
      "isEnabled": true,
      "createdAt": "2026-07-14T13:07:15.846Z",
      "claimedBy": []
    },
    {
      "code": "TM-GFT-Q98G-98RH",
      "rewardAmount": 0.1,
      "maxClaims": 1,
      "claimsCount": 0,
      "isEnabled": true,
      "createdAt": "2026-07-14T13:07:15.846Z",
      "claimedBy": []
    },
    {
      "code": "TM-GFT-FHZG-SEGN",
      "rewardAmount": 0.1,
      "maxClaims": 1,
      "claimsCount": 0,
      "isEnabled": true,
      "createdAt": "2026-07-14T13:07:15.846Z",
      "claimedBy": []
    },
    {
      "code": "TM-GFT-FQ1R-T77S",
      "rewardAmount": 0.1,
      "maxClaims": 1,
      "claimsCount": 0,
      "isEnabled": true,
      "createdAt": "2026-07-14T13:07:15.846Z",
      "claimedBy": []
    },
    {
      "code": "TM-GFT-BOFL-QVQX",
      "rewardAmount": 0.1,
      "maxClaims": 1,
      "claimsCount": 0,
      "isEnabled": true,
      "createdAt": "2026-07-14T13:07:15.846Z",
      "claimedBy": []
    },
    {
      "code": "TM-GFT-8WYS-THD7",
      "rewardAmount": 0.1,
      "maxClaims": 1,
      "claimsCount": 0,
      "isEnabled": true,
      "createdAt": "2026-07-14T13:07:15.846Z",
      "claimedBy": []
    },
    {
      "code": "TM-GFT-NQYN-H5MN",
      "rewardAmount": 0.1,
      "maxClaims": 1,
      "claimsCount": 0,
      "isEnabled": true,
      "createdAt": "2026-07-14T13:07:15.846Z",
      "claimedBy": []
    },
    {
      "code": "TM-GFT-FLPR-0ELM",
      "rewardAmount": 0.1,
      "maxClaims": 1,
      "claimsCount": 1,
      "isEnabled": true,
      "createdAt": "2026-07-14T13:07:15.847Z",
      "claimedBy": [
        "111111111"
      ]
    },
    {
      "code": "TM-GFT-9BKX-NJXZ",
      "rewardAmount": 0.1,
      "maxClaims": 1,
      "claimsCount": 1,
      "isEnabled": true,
      "createdAt": "2026-07-14T13:07:15.847Z",
      "claimedBy": [
        "111111111"
      ]
    },
    {
      "code": "TM-GFT-T0SR-WXDG",
      "rewardAmount": 0.1,
      "maxClaims": 1,
      "claimsCount": 1,
      "isEnabled": true,
      "createdAt": "2026-07-14T13:07:15.847Z",
      "claimedBy": [
        "222222222"
      ]
    },
    {
      "code": "TM-GFT-1006-K2RZ",
      "rewardAmount": 0.1,
      "maxClaims": 1,
      "claimsCount": 0,
      "isEnabled": true,
      "createdAt": "2026-07-14T13:07:15.847Z",
      "claimedBy": []
    },
    {
      "code": "TM-GFT-3FTT-5LZK",
      "rewardAmount": 0.1,
      "maxClaims": 1,
      "claimsCount": 0,
      "isEnabled": true,
      "createdAt": "2026-07-14T13:07:15.847Z",
      "claimedBy": []
    },
    {
      "code": "TM-GFT-JMGJ-2NY1",
      "rewardAmount": 0.1,
      "maxClaims": 1,
      "claimsCount": 0,
      "isEnabled": true,
      "createdAt": "2026-07-14T13:07:15.847Z",
      "claimedBy": []
    },
    {
      "code": "TM-GFT-CLFH-O9KE",
      "rewardAmount": 0.1,
      "maxClaims": 1,
      "claimsCount": 0,
      "isEnabled": true,
      "createdAt": "2026-07-14T13:07:15.847Z",
      "claimedBy": []
    },
    {
      "code": "TM-GFT-6HRT-679P",
      "rewardAmount": 0.1,
      "maxClaims": 1,
      "claimsCount": 0,
      "isEnabled": true,
      "createdAt": "2026-07-14T13:07:15.847Z",
      "claimedBy": []
    },
    {
      "code": "TM-GFT-GDM7-FV4J",
      "rewardAmount": 0.1,
      "maxClaims": 1,
      "claimsCount": 0,
      "isEnabled": true,
      "createdAt": "2026-07-14T13:07:15.847Z",
      "claimedBy": []
    },
    {
      "code": "TM-GFT-QCY5-6A3C",
      "rewardAmount": 0.1,
      "maxClaims": 1,
      "claimsCount": 0,
      "isEnabled": true,
      "createdAt": "2026-07-14T13:07:15.847Z",
      "claimedBy": []
    },
    {
      "code": "TM-GFT-6N0R-XDQD",
      "rewardAmount": 0.1,
      "maxClaims": 1,
      "claimsCount": 0,
      "isEnabled": true,
      "createdAt": "2026-07-14T13:07:15.847Z",
      "claimedBy": []
    },
    {
      "code": "TM-GFT-H12R-XDJO",
      "rewardAmount": 0.1,
      "maxClaims": 1,
      "claimsCount": 0,
      "isEnabled": true,
      "createdAt": "2026-07-14T13:07:15.847Z",
      "claimedBy": []
    },
    {
      "code": "TM-GFT-WZLJ-O57V",
      "rewardAmount": 0.1,
      "maxClaims": 1,
      "claimsCount": 0,
      "isEnabled": true,
      "createdAt": "2026-07-14T13:07:15.847Z",
      "claimedBy": []
    },
    {
      "code": "TM-GFT-LGYG-D6AT",
      "rewardAmount": 0.1,
      "maxClaims": 1,
      "claimsCount": 0,
      "isEnabled": true,
      "createdAt": "2026-07-14T13:07:15.847Z",
      "claimedBy": []
    },
    {
      "code": "TM-GFT-OOSN-3WQV",
      "rewardAmount": 0.1,
      "maxClaims": 1,
      "claimsCount": 0,
      "isEnabled": true,
      "createdAt": "2026-07-14T13:07:15.847Z",
      "claimedBy": []
    },
    {
      "code": "TM-GFT-GX3H-C2DE",
      "rewardAmount": 0.1,
      "maxClaims": 1,
      "claimsCount": 0,
      "isEnabled": true,
      "createdAt": "2026-07-14T13:07:15.847Z",
      "claimedBy": []
    },
    {
      "code": "TM-GFT-EFQO-1FZ6",
      "rewardAmount": 0.1,
      "maxClaims": 1,
      "claimsCount": 0,
      "isEnabled": true,
      "createdAt": "2026-07-14T13:07:15.847Z",
      "claimedBy": []
    },
    {
      "code": "TM-GFT-LGEU-PL8Y",
      "rewardAmount": 0.1,
      "maxClaims": 1,
      "claimsCount": 0,
      "isEnabled": true,
      "createdAt": "2026-07-14T13:07:15.847Z",
      "claimedBy": []
    },
    {
      "code": "TM-GFT-1P9C-IY7T",
      "rewardAmount": 0.1,
      "maxClaims": 1,
      "claimsCount": 0,
      "isEnabled": true,
      "createdAt": "2026-07-14T13:07:15.847Z",
      "claimedBy": []
    },
    {
      "code": "TM-GFT-0WT4-2QT0",
      "rewardAmount": 0.1,
      "maxClaims": 1,
      "claimsCount": 0,
      "isEnabled": true,
      "createdAt": "2026-07-14T13:07:15.847Z",
      "claimedBy": []
    },
    {
      "code": "TM-GFT-5HVQ-G3BQ",
      "rewardAmount": 0.1,
      "maxClaims": 1,
      "claimsCount": 0,
      "isEnabled": true,
      "createdAt": "2026-07-14T13:07:15.847Z",
      "claimedBy": []
    },
    {
      "code": "TM-GFT-3E8G-5JIR",
      "rewardAmount": 0.1,
      "maxClaims": 1,
      "claimsCount": 0,
      "isEnabled": true,
      "createdAt": "2026-07-14T13:07:15.847Z",
      "claimedBy": []
    },
    {
      "code": "TM-GFT-2WOE-Z10R",
      "rewardAmount": 0.1,
      "maxClaims": 1,
      "claimsCount": 0,
      "isEnabled": true,
      "createdAt": "2026-07-14T13:07:15.847Z",
      "claimedBy": []
    },
    {
      "code": "TM-GFT-CCI5-6UU4",
      "rewardAmount": 0.1,
      "maxClaims": 1,
      "claimsCount": 0,
      "isEnabled": true,
      "createdAt": "2026-07-14T13:07:15.847Z",
      "claimedBy": []
    },
    {
      "code": "TM-GFT-HOEY-0G8Y",
      "rewardAmount": 0.1,
      "maxClaims": 1,
      "claimsCount": 0,
      "isEnabled": true,
      "createdAt": "2026-07-14T13:07:15.847Z",
      "claimedBy": []
    },
    {
      "code": "TM-GFT-DBO6-EYVC",
      "rewardAmount": 0.1,
      "maxClaims": 1,
      "claimsCount": 0,
      "isEnabled": true,
      "createdAt": "2026-07-14T13:07:15.847Z",
      "claimedBy": []
    },
    {
      "code": "TM-GFT-ED8Q-3JBD",
      "rewardAmount": 0.1,
      "maxClaims": 1,
      "claimsCount": 0,
      "isEnabled": true,
      "createdAt": "2026-07-14T13:07:15.847Z",
      "claimedBy": []
    },
    {
      "code": "TM-GFT-WLKR-BYSC",
      "rewardAmount": 0.1,
      "maxClaims": 1,
      "claimsCount": 0,
      "isEnabled": true,
      "createdAt": "2026-07-14T13:07:15.847Z",
      "claimedBy": []
    },
    {
      "code": "TM-GFT-81NL-SJ6E",
      "rewardAmount": 0.1,
      "maxClaims": 1,
      "claimsCount": 0,
      "isEnabled": true,
      "createdAt": "2026-07-14T13:07:15.847Z",
      "claimedBy": []
    },
    {
      "code": "TM-GFT-PZY8-OH5D",
      "rewardAmount": 0.1,
      "maxClaims": 1,
      "claimsCount": 0,
      "isEnabled": true,
      "createdAt": "2026-07-14T13:07:15.847Z",
      "claimedBy": []
    },
    {
      "code": "TM-GFT-W2U2-9T70",
      "rewardAmount": 0.1,
      "maxClaims": 1,
      "claimsCount": 0,
      "isEnabled": true,
      "createdAt": "2026-07-14T13:07:15.847Z",
      "claimedBy": []
    },
    {
      "code": "TM-GFT-DCNK-SCAB",
      "rewardAmount": 0.1,
      "maxClaims": 1,
      "claimsCount": 0,
      "isEnabled": true,
      "createdAt": "2026-07-14T13:07:15.847Z",
      "claimedBy": []
    },
    {
      "code": "TM-GFT-N79H-MLNT",
      "rewardAmount": 0.1,
      "maxClaims": 1,
      "claimsCount": 0,
      "isEnabled": true,
      "createdAt": "2026-07-14T13:07:15.847Z",
      "claimedBy": []
    },
    {
      "code": "TM-GFT-I9T2-3M9U",
      "rewardAmount": 0.1,
      "maxClaims": 1,
      "claimsCount": 0,
      "isEnabled": true,
      "createdAt": "2026-07-14T13:07:15.847Z",
      "claimedBy": []
    },
    {
      "code": "TM-GFT-E963-XACY",
      "rewardAmount": 0.1,
      "maxClaims": 1,
      "claimsCount": 0,
      "isEnabled": true,
      "createdAt": "2026-07-14T13:07:15.847Z",
      "claimedBy": []
    },
    {
      "code": "TM-GFT-9RAW-GAF3",
      "rewardAmount": 0.1,
      "maxClaims": 1,
      "claimsCount": 0,
      "isEnabled": true,
      "createdAt": "2026-07-14T13:07:15.847Z",
      "claimedBy": []
    },
    {
      "code": "TM-GFT-O43N-HYQ1",
      "rewardAmount": 0.1,
      "maxClaims": 1,
      "claimsCount": 0,
      "isEnabled": true,
      "createdAt": "2026-07-14T13:07:15.847Z",
      "claimedBy": []
    },
    {
      "code": "TM-GFT-IBPO-8N8T",
      "rewardAmount": 0.1,
      "maxClaims": 1,
      "claimsCount": 0,
      "isEnabled": true,
      "createdAt": "2026-07-14T13:07:15.847Z",
      "claimedBy": []
    },
    {
      "code": "TM-GFT-UZY9-48E5",
      "rewardAmount": 0.1,
      "maxClaims": 1,
      "claimsCount": 0,
      "isEnabled": true,
      "createdAt": "2026-07-14T13:07:15.847Z",
      "claimedBy": []
    },
    {
      "code": "TM-GFT-7T6V-FJX0",
      "rewardAmount": 0.1,
      "maxClaims": 1,
      "claimsCount": 0,
      "isEnabled": true,
      "createdAt": "2026-07-14T13:07:15.847Z",
      "claimedBy": []
    },
    {
      "code": "TM-GFT-3BNU-1W4X",
      "rewardAmount": 0.1,
      "maxClaims": 1,
      "claimsCount": 0,
      "isEnabled": true,
      "createdAt": "2026-07-14T13:07:15.847Z",
      "claimedBy": []
    },
    {
      "code": "TM-GFT-1FA7-O32E",
      "rewardAmount": 0.1,
      "maxClaims": 1,
      "claimsCount": 0,
      "isEnabled": true,
      "createdAt": "2026-07-14T13:07:15.847Z",
      "claimedBy": []
    },
    {
      "code": "TM-GFT-61A8-XT9I",
      "rewardAmount": 0.1,
      "maxClaims": 1,
      "claimsCount": 0,
      "isEnabled": true,
      "createdAt": "2026-07-14T13:07:15.847Z",
      "claimedBy": []
    },
    {
      "code": "TM-GFT-3VY6-G90G",
      "rewardAmount": 0.1,
      "maxClaims": 1,
      "claimsCount": 0,
      "isEnabled": true,
      "createdAt": "2026-07-14T13:07:15.847Z",
      "claimedBy": []
    },
    {
      "code": "TM-GFT-93OQ-1C3N",
      "rewardAmount": 0.1,
      "maxClaims": 1,
      "claimsCount": 0,
      "isEnabled": true,
      "createdAt": "2026-07-14T13:07:15.847Z",
      "claimedBy": []
    },
    {
      "code": "TM-GFT-G1MA-9OV4",
      "rewardAmount": 0.1,
      "maxClaims": 1,
      "claimsCount": 0,
      "isEnabled": true,
      "createdAt": "2026-07-14T13:07:15.847Z",
      "claimedBy": []
    },
    {
      "code": "TM-GFT-MLP7-8EBN",
      "rewardAmount": 0.1,
      "maxClaims": 1,
      "claimsCount": 0,
      "isEnabled": true,
      "createdAt": "2026-07-14T13:07:15.847Z",
      "claimedBy": []
    },
    {
      "code": "TM-GFT-NQW0-2UCQ",
      "rewardAmount": 0.1,
      "maxClaims": 1,
      "claimsCount": 0,
      "isEnabled": true,
      "createdAt": "2026-07-14T13:07:15.847Z",
      "claimedBy": []
    },
    {
      "code": "TM-GFT-9G81-HQS0",
      "rewardAmount": 0.1,
      "maxClaims": 1,
      "claimsCount": 0,
      "isEnabled": true,
      "createdAt": "2026-07-14T13:07:15.847Z",
      "claimedBy": []
    },
    {
      "code": "TM-GFT-2DI8-UTH5",
      "rewardAmount": 0.1,
      "maxClaims": 1,
      "claimsCount": 0,
      "isEnabled": true,
      "createdAt": "2026-07-14T13:07:15.847Z",
      "claimedBy": []
    },
    {
      "code": "TM-GFT-40W4-PMTI",
      "rewardAmount": 0.1,
      "maxClaims": 1,
      "claimsCount": 0,
      "isEnabled": true,
      "createdAt": "2026-07-14T13:07:15.847Z",
      "claimedBy": []
    },
    {
      "code": "TM-GFT-PQGZ-ZJAB",
      "rewardAmount": 0.1,
      "maxClaims": 1,
      "claimsCount": 0,
      "isEnabled": true,
      "createdAt": "2026-07-14T13:07:15.847Z",
      "claimedBy": []
    },
    {
      "code": "TM-GFT-PO1O-Z5KW",
      "rewardAmount": 0.1,
      "maxClaims": 1,
      "claimsCount": 0,
      "isEnabled": true,
      "createdAt": "2026-07-14T13:07:15.847Z",
      "claimedBy": []
    },
    {
      "code": "TM-GFT-FEO1-M5PR",
      "rewardAmount": 0.1,
      "maxClaims": 1,
      "claimsCount": 0,
      "isEnabled": true,
      "createdAt": "2026-07-14T13:07:15.847Z",
      "claimedBy": []
    },
    {
      "code": "TM-GFT-D04F-ST3K",
      "rewardAmount": 0.1,
      "maxClaims": 1,
      "claimsCount": 0,
      "isEnabled": true,
      "createdAt": "2026-07-14T13:07:15.847Z",
      "claimedBy": []
    },
    {
      "code": "TM-GFT-9NV9-01GI",
      "rewardAmount": 0.1,
      "maxClaims": 1,
      "claimsCount": 0,
      "isEnabled": true,
      "createdAt": "2026-07-14T13:07:15.847Z",
      "claimedBy": []
    },
    {
      "code": "TM-GFT-TXJ0-HFL8",
      "rewardAmount": 0.1,
      "maxClaims": 1,
      "claimsCount": 0,
      "isEnabled": true,
      "createdAt": "2026-07-14T13:07:15.847Z",
      "claimedBy": []
    },
    {
      "code": "TM-GFT-LR4J-MIE9",
      "rewardAmount": 0.1,
      "maxClaims": 1,
      "claimsCount": 0,
      "isEnabled": true,
      "createdAt": "2026-07-14T13:07:15.847Z",
      "claimedBy": []
    },
    {
      "code": "TM-GFT-MT1L-0LC5",
      "rewardAmount": 0.1,
      "maxClaims": 1,
      "claimsCount": 0,
      "isEnabled": true,
      "createdAt": "2026-07-14T13:07:15.847Z",
      "claimedBy": []
    },
    {
      "code": "TM-GFT-LHYF-4GEM",
      "rewardAmount": 0.1,
      "maxClaims": 1,
      "claimsCount": 0,
      "isEnabled": true,
      "createdAt": "2026-07-14T13:07:15.847Z",
      "claimedBy": []
    },
    {
      "code": "TM-GFT-LH2I-S2HS",
      "rewardAmount": 0.1,
      "maxClaims": 1,
      "claimsCount": 0,
      "isEnabled": true,
      "createdAt": "2026-07-14T13:07:15.847Z",
      "claimedBy": []
    },
    {
      "code": "TM-GFT-QMVE-G6LP",
      "rewardAmount": 0.1,
      "maxClaims": 1,
      "claimsCount": 0,
      "isEnabled": true,
      "createdAt": "2026-07-14T13:07:15.847Z",
      "claimedBy": []
    },
    {
      "code": "TM-GFT-JEPH-XIF9",
      "rewardAmount": 0.1,
      "maxClaims": 1,
      "claimsCount": 0,
      "isEnabled": true,
      "createdAt": "2026-07-14T13:07:15.847Z",
      "claimedBy": []
    },
    {
      "code": "TM-GFT-X1YO-0VIY",
      "rewardAmount": 0.1,
      "maxClaims": 1,
      "claimsCount": 0,
      "isEnabled": true,
      "createdAt": "2026-07-14T13:07:15.847Z",
      "claimedBy": []
    },
    {
      "code": "TM-GFT-AMSE-R4WI",
      "rewardAmount": 0.1,
      "maxClaims": 1,
      "claimsCount": 0,
      "isEnabled": true,
      "createdAt": "2026-07-14T13:07:15.847Z",
      "claimedBy": []
    },
    {
      "code": "TM-GFT-SBRK-Q2X1",
      "rewardAmount": 0.1,
      "maxClaims": 1,
      "claimsCount": 0,
      "isEnabled": true,
      "createdAt": "2026-07-14T13:07:15.847Z",
      "claimedBy": []
    },
    {
      "code": "TM-GFT-K72G-Z3Z3",
      "rewardAmount": 0.1,
      "maxClaims": 1,
      "claimsCount": 0,
      "isEnabled": true,
      "createdAt": "2026-07-14T13:07:15.847Z",
      "claimedBy": []
    },
    {
      "code": "TM-GFT-6SMC-JG7H",
      "rewardAmount": 0.1,
      "maxClaims": 1,
      "claimsCount": 0,
      "isEnabled": true,
      "createdAt": "2026-07-14T13:07:15.847Z",
      "claimedBy": []
    },
    {
      "code": "TM-GFT-LVLM-2ZZB",
      "rewardAmount": 0.1,
      "maxClaims": 1,
      "claimsCount": 0,
      "isEnabled": true,
      "createdAt": "2026-07-14T13:07:15.847Z",
      "claimedBy": []
    },
    {
      "code": "TM-GFT-WEV4-PX0G",
      "rewardAmount": 0.1,
      "maxClaims": 1,
      "claimsCount": 0,
      "isEnabled": true,
      "createdAt": "2026-07-14T13:07:15.847Z",
      "claimedBy": []
    },
    {
      "code": "TM-GFT-8KCM-9KXN",
      "rewardAmount": 0.1,
      "maxClaims": 1,
      "claimsCount": 0,
      "isEnabled": true,
      "createdAt": "2026-07-14T13:07:15.847Z",
      "claimedBy": []
    },
    {
      "code": "TM-GFT-JYQD-7ROO",
      "rewardAmount": 0.1,
      "maxClaims": 1,
      "claimsCount": 0,
      "isEnabled": true,
      "createdAt": "2026-07-14T13:07:15.847Z",
      "claimedBy": []
    },
    {
      "code": "TM-GFT-DTQO-I9S0",
      "rewardAmount": 0.1,
      "maxClaims": 1,
      "claimsCount": 0,
      "isEnabled": true,
      "createdAt": "2026-07-14T13:07:15.847Z",
      "claimedBy": []
    },
    {
      "code": "TM-GFT-AH4T-OOUN",
      "rewardAmount": 0.1,
      "maxClaims": 1,
      "claimsCount": 0,
      "isEnabled": true,
      "createdAt": "2026-07-14T13:07:15.847Z",
      "claimedBy": []
    },
    {
      "code": "TM-GFT-JZSZ-S0LV",
      "rewardAmount": 0.1,
      "maxClaims": 1,
      "claimsCount": 0,
      "isEnabled": true,
      "createdAt": "2026-07-14T13:07:15.847Z",
      "claimedBy": []
    },
    {
      "code": "TM-GFT-LOX4-EPNX",
      "rewardAmount": 0.1,
      "maxClaims": 1,
      "claimsCount": 0,
      "isEnabled": true,
      "createdAt": "2026-07-14T13:07:15.847Z",
      "claimedBy": []
    },
    {
      "code": "TM-GFT-0FIT-5CO0",
      "rewardAmount": 0.1,
      "maxClaims": 1,
      "claimsCount": 0,
      "isEnabled": true,
      "createdAt": "2026-07-14T13:07:15.847Z",
      "claimedBy": []
    },
    {
      "code": "TM-GFT-4M7F-0NI6",
      "rewardAmount": 0.1,
      "maxClaims": 1,
      "claimsCount": 0,
      "isEnabled": true,
      "createdAt": "2026-07-14T13:07:15.847Z",
      "claimedBy": []
    },
    {
      "code": "TM-GFT-XMDH-1IS6",
      "rewardAmount": 0.1,
      "maxClaims": 1,
      "claimsCount": 0,
      "isEnabled": true,
      "createdAt": "2026-07-14T13:07:15.847Z",
      "claimedBy": []
    },
    {
      "code": "TM-GFT-Y875-DMSV",
      "rewardAmount": 0.1,
      "maxClaims": 1,
      "claimsCount": 0,
      "isEnabled": true,
      "createdAt": "2026-07-14T13:07:15.847Z",
      "claimedBy": []
    },
    {
      "code": "TM-GFT-MT0Q-WTZL",
      "rewardAmount": 0.1,
      "maxClaims": 1,
      "claimsCount": 0,
      "isEnabled": true,
      "createdAt": "2026-07-14T13:07:15.847Z",
      "claimedBy": []
    },
    {
      "code": "TM-GFT-BFYK-6STZ",
      "rewardAmount": 0.1,
      "maxClaims": 1,
      "claimsCount": 0,
      "isEnabled": true,
      "createdAt": "2026-07-14T13:07:15.847Z",
      "claimedBy": []
    },
    {
      "code": "TM-GFT-SV1W-2TAE",
      "rewardAmount": 0.1,
      "maxClaims": 1,
      "claimsCount": 0,
      "isEnabled": true,
      "createdAt": "2026-07-14T13:07:15.847Z",
      "claimedBy": []
    },
    {
      "code": "TM-GFT-27T3-Y7ZX",
      "rewardAmount": 0.1,
      "maxClaims": 1,
      "claimsCount": 0,
      "isEnabled": true,
      "createdAt": "2026-07-14T13:07:15.847Z",
      "claimedBy": []
    },
    {
      "code": "TM-GFT-0WGY-ZCVD",
      "rewardAmount": 0.1,
      "maxClaims": 1,
      "claimsCount": 0,
      "isEnabled": true,
      "createdAt": "2026-07-14T13:07:15.847Z",
      "claimedBy": []
    },
    {
      "code": "TM-GFT-50E2-A207",
      "rewardAmount": 0.1,
      "maxClaims": 1,
      "claimsCount": 0,
      "isEnabled": true,
      "createdAt": "2026-07-14T13:07:15.847Z",
      "claimedBy": []
    },
    {
      "code": "TM-GFT-AKBJ-7Y9U",
      "rewardAmount": 0.1,
      "maxClaims": 1,
      "claimsCount": 0,
      "isEnabled": true,
      "createdAt": "2026-07-14T13:07:15.847Z",
      "claimedBy": []
    },
    {
      "code": "TM-GFT-9Z4Q-P7AO",
      "rewardAmount": 0.1,
      "maxClaims": 1,
      "claimsCount": 0,
      "isEnabled": true,
      "createdAt": "2026-07-14T13:07:15.847Z",
      "claimedBy": []
    },
    {
      "code": "TM-GFT-OQ3L-5Y17",
      "rewardAmount": 0.1,
      "maxClaims": 1,
      "claimsCount": 0,
      "isEnabled": true,
      "createdAt": "2026-07-14T13:07:15.847Z",
      "claimedBy": []
    },
    {
      "code": "TM-GFT-F1B3-206T",
      "rewardAmount": 0.1,
      "maxClaims": 1,
      "claimsCount": 0,
      "isEnabled": true,
      "createdAt": "2026-07-14T13:07:15.847Z",
      "claimedBy": []
    },
    {
      "code": "TM-GFT-2K96-K668",
      "rewardAmount": 0.1,
      "maxClaims": 1,
      "claimsCount": 0,
      "isEnabled": true,
      "createdAt": "2026-07-14T13:07:15.847Z",
      "claimedBy": []
    },
    {
      "code": "TM-GFT-Y320-ZGRT",
      "rewardAmount": 0.1,
      "maxClaims": 1,
      "claimsCount": 0,
      "isEnabled": true,
      "createdAt": "2026-07-14T13:07:15.847Z",
      "claimedBy": []
    }
  ]
}